stgem/__init__.py
stgem/config.py
stgem/exceptions.py
stgem/features.py
stgem/limit.py
stgem/logging.py
stgem/plot.py
stgem/rng.py
stgem/search.py
stgem/sut.py
stgem/task.py
stgem/util.py
stgem/monitor/__init__.py
stgem/monitor/stl.py
stgem/monitor/pystl/__init__.py
stgem/monitor/pystl/parser.py
stgem/monitor/pystl/robustness.py
stgem/monitor/pystl/stlLexer.py
stgem/monitor/pystl/stlParser.py
stgem/monitor/pystl/visitor.py
stgem/system/__init__.py
stgem/system/apros.py
stgem/system/fmu.py
stgem/system/gym.py
stgem/system/matlab.py
stgem/system/mo3d.py
stgem/testgenerator/__init__.py
stgem/testgenerator/model.py
stgem/testgenerator/sampler.py
stgem/testgenerator/diffusion/__init__.py
stgem/testgenerator/diffusion/ddpm.py
stgem/testgenerator/diffusion/generator.py
stgem/testgenerator/diffusion/model.py
stgem/testgenerator/ogan/__init__.py
stgem/testgenerator/ogan/generator.py
stgem/testgenerator/ogan/mlm.py
stgem/testgenerator/ogan/model.py
stgem/testgenerator/random/__init__.py
stgem/testgenerator/random/generator.py
stgem/testgenerator/random/model.py
stgem/testgenerator/wogan/__init__.py
stgem/testgenerator/wogan/analyzer.py
stgem/testgenerator/wogan/generator.py
stgem/testgenerator/wogan/mlm.py
stgem/testgenerator/wogan/model.py
stgem/testgenerator/wogan/sampler.py
stgem/testsuitegenerator/__init__.py
stgem/testsuitegenerator/parameters.py
stgem/testsuitegenerator/diffusion/__init__.py
stgem/testsuitegenerator/diffusion/diffusion.py
stgem/testsuitegenerator/ogan/__init__.py
stgem/testsuitegenerator/ogan/ogan.py
stgem/testsuitegenerator/wogan/__init__.py
stgem/testsuitegenerator/wogan/wogan.py
stgem-2.0.1.dist-info/licenses/LICENSE
stgem-2.0.1.dist-info/METADATA
stgem-2.0.1.dist-info/WHEEL
stgem-2.0.1.dist-info/top_level.txt
stgem-2.0.1.dist-info/RECORD
