Metadata-Version: 2.4
Name: stgem
Version: 2.0.1
Summary: System Testing Using Generative Models
Author-email: Ivan Porres <ivan.porres@abo.fi>, Jarkko Peltomäki <jarkko.peltomaki@abo.fi>, Valentin Soloviev <valentin.soloviev@abo.fi>, Erik Wihlman <erik.wihlman@abo.fi>, Jesper Winsten <jesper.winsten@abo.fi>
License-Expression: MIT
Project-URL: Homepage, https://gitlab.abo.fi/stc/stgem2
Project-URL: Issues, https://gitlab.abo.fi/stc/stgem2/issues
Project-URL: Documentation, https://gitlab.abo.fi/stc/stgem2
Keywords: testing,generative AI
Classifier: Intended Audience :: Science/Research
Classifier: Programming Language :: Python :: 3
Classifier: Operating System :: OS Independent
Requires-Python: >=3.11
License-File: LICENSE
Requires-Dist: antlr4-python3-runtime==4.13.0
Requires-Dist: dill~=0.3.4
Requires-Dist: tensorflow~=2.16.1
Requires-Dist: torch~=2.2.1
Requires-Dist: numpy<2.0.0
Requires-Dist: matplotlib~=3.8.3
Requires-Dist: bunch_py3~=2.0.0
Requires-Dist: pandas~=2.2.1
Requires-Dist: joblib~=1.3.2
Requires-Dist: gymnasium
Requires-Dist: scipy
Requires-Dist: alive_progress
Requires-Dist: seaborn
Requires-Dist: fmpy
Requires-Dist: grpcio
Requires-Dist: grpcio_tools
Requires-Dist: protobuf
Requires-Dist: scikit-learn
Requires-Dist: commonmark
Requires-Dist: myst-parser
Requires-Dist: sphinx_rtd_theme
Requires-Dist: plotly
Dynamic: license-file
